JLC2KiCadLib/JLC2KiCadLib.py
JLC2KiCadLib/__init__.py
JLC2KiCadLib/helper.py
JLC2KiCadLib/footprint/__init__.py
JLC2KiCadLib/footprint/footprint.py
JLC2KiCadLib/footprint/footprint_handlers.py
JLC2KiCadLib/footprint/model3d.py
JLC2KiCadLib/symbol/__init__.py
JLC2KiCadLib/symbol/symbol.py
JLC2KiCadLib/symbol/symbol_handlers.py
jlc2kicadlib-1.2.1.dist-info/METADATA
jlc2kicadlib-1.2.1.dist-info/WHEEL
jlc2kicadlib-1.2.1.dist-info/entry_points.txt
jlc2kicadlib-1.2.1.dist-info/RECORD
