Metadata-Version: 2.4
Name: JLC2KiCadLib
Version: 1.2.1
Summary: JLC2KiCad_lib is a python script that generate a component library (symbol, footprint and 3D model) for KiCad from the JLCPCB/easyEDA library.
Project-URL: Homepage, https://github.com/TousstNicolas/JLC2KiCad_lib
Project-URL: Issues, https://github.com/TousstNicolas/JLC2KiCad_lib/issues
Author: TousstNicolas
License-Expression: MIT
Classifier: License :: OSI Approved :: MIT License
Classifier: Operating System :: OS Independent
Classifier: Programming Language :: Python :: 3.8
Classifier: Topic :: Scientific/Engineering :: Electronic Design Automation (EDA)
Requires-Python: >=3.8
Requires-Dist: kicadmodtree
Requires-Dist: requests
